AUTHORS
LICENSE
MANIFEST.in
README.rst
setup.py
django_nani.egg-info/PKG-INFO
django_nani.egg-info/SOURCES.txt
django_nani.egg-info/dependency_links.txt
django_nani.egg-info/not-zip-safe
django_nani.egg-info/requires.txt
django_nani.egg-info/top_level.txt
nani/__init__.py
nani/admin.py
nani/descriptors.py
nani/exceptions.py
nani/fieldtranslator.py
nani/forms.py
nani/manager.py
nani/models.py
nani/utils.py
nani/compat/__init__.py
nani/compat/date.py
nani/templates/admin/nani/change_form.html
nani/templates/admin/nani/deletion_not_allowed.html
nani/test_utils/__init__.py
nani/test_utils/context_managers.py
nani/test_utils/data.py
nani/test_utils/fixtures.py
nani/test_utils/request_factory.py
nani/test_utils/testcase.py
nani/tests/__init__.py
nani/tests/admin.py
nani/tests/basic.py
nani/tests/dates.py
nani/tests/docs.py
nani/tests/forms.py
nani/tests/ordering.py
nani/tests/query.py
nani/tests/related.py